[{"domain": "www.zhihu.com", "expiry": 1554462448.140527, "httpOnly": false, "name": "tgw_l7_route", "path": "/", "secure": false, "value": "f2979fdd289e2265b2f12e4f4a478330"}, {"domain": ".zhihu.com", "expiry": 1557053577.671925, "httpOnly": true, "name": "z_c0", "path": "/", "secure": false, "value": "\"2|1:0|10:1554461577|4:z_c0|92:Mi4xVnRNVUR3QUFBQUFBSUNlTjVGczdEeWNBQUFDRUFsVk5pY0RPWEFEckxJeFAzNDN0QzdoZWtPZnJJbUREU3dZMDRB|fd04725b35e8df4b54eec4bfbcdcc6047c5baa37cb9e7d450db44a17fd0bc557\""}, {"domain": ".zhihu.com", "expiry": 1649069578.175387, "httpOnly": false, "name": "q_c1", "path": "/", "secure": false, "value": "0016013b58994339a8d5ce670254918c|1554461578000|1554461578000"}, {"domain": ".zhihu.com", "expiry": 1617533548.140604, "httpOnly": false, "name": "_zap", "path": "/", "secure": false, "value": "c22908e3-1f9c-4cd3-88b5-cbe7e210f049"}, {"domain": ".zhihu.com", "expiry": 1649069550.053064, "httpOnly": false, "name": "d_c0", "path": "/", "secure": false, "value": "\"ACAnjeRbOw-PTr3n85OD5UZm_0JGBjdysdU=|1554461549\""}, {"domain": ".zhihu.com", "httpOnly": false, "name": "_xsrf", "path": "/", "secure": false, "value": "0a230dd0-97d4-4f67-8ae2-a5e698c926cf"}, {"domain": ".zhihu.com", "expiry": 1557053550.209424, "httpOnly": true, "name": "capsion_ticket", "path": "/", "secure": false, "value": "\"2|1:0|10:1554461550|14:capsion_ticket|44:ZDY2NjMzZWEyMWY5NDQ5NGEzOWFmMDM3YjkyMDc5NzY=|a2364b5b0416c11581c58e56d99acd28480cbe9a0ed86b856e8d085846fc7b63\""}, {"domain": ".zhihu.com", "expiry": 1557053579, "httpOnly": false, "name": "tst", "path": "/", "secure": false, "value": "r"}, {"domain": ".zhihu.com", "expiry": 1617533580, "httpOnly": false, "name": "__gads", "path": "/", "secure": false, "value": "ID=ecfbed34374e8cac:T=1554461580:S=ALNI_MZI0uy4lcTExEKgiQmH4WsrcQFRKQ"}]